msl/__init__.py
msl/examples/__init__.py
msl/examples/package_manager/__init__.py
msl/package_manager/__init__.py
msl/package_manager/authorise.py
msl/package_manager/cli.py
msl/package_manager/cli_argparse.py
msl/package_manager/cli_authorise.py
msl/package_manager/cli_create.py
msl/package_manager/cli_install.py
msl/package_manager/cli_list.py
msl/package_manager/cli_uninstall.py
msl/package_manager/cli_update.py
msl/package_manager/create.py
msl/package_manager/install.py
msl/package_manager/uninstall.py
msl/package_manager/update.py
msl/package_manager/utils.py
msl/package_manager/template/.coveragerc
msl/package_manager/template/.gitignore
msl/package_manager/template/AUTHORS.rst
msl/package_manager/template/CHANGES.rst
msl/package_manager/template/LICENSE.txt
msl/package_manager/template/MANIFEST.in
msl/package_manager/template/README.rst
msl/package_manager/template/condatests.py.template
msl/package_manager/template/setup.cfg
msl/package_manager/template/setup.py.template
msl/package_manager/template/${namespace}/__init__.py.template
msl/package_manager/template/${namespace}/${package}/__init__.py.template
msl/package_manager/template/${namespace}/examples/__init__.py.template
msl/package_manager/template/${namespace}/examples/${package}/__init__.py.template
msl/package_manager/template/docs/authors.rst
msl/package_manager/template/docs/changelog.rst
msl/package_manager/template/docs/conf.py.template
msl/package_manager/template/docs/index.rst
msl/package_manager/template/docs/license.rst
msl/package_manager/template/docs/_static/README
msl/package_manager/template/tests/README
msl_package_manager-2.5.4.dist-info/AUTHORS.rst
msl_package_manager-2.5.4.dist-info/LICENSE.txt
msl_package_manager-2.5.4.dist-info/METADATA
msl_package_manager-2.5.4.dist-info/WHEEL
msl_package_manager-2.5.4.dist-info/entry_points.txt
msl_package_manager-2.5.4.dist-info/top_level.txt
msl_package_manager-2.5.4.dist-info/RECORD
