Metadata-Version: 2.1
Name: msl-package-manager
Version: 2.5.4
Summary: Install, uninstall, update, list and create MSL packages
Home-page: https://github.com/MSLNZ/msl-package-manager
Author: Measurement Standards Laboratory of New Zealand
Author-email: info@measurement.govt.nz
License: MIT
Platform: any
Classifier: Development Status :: 4 - Beta
Classifier: Environment :: Console
Classifier: Intended Audience :: Science/Research
Classifier: Intended Audience :: Developers
Classifier: License :: OSI Approved :: MIT License
Classifier: Operating System :: OS Independent
Classifier: Programming Language :: Python
Classifier: Programming Language :: Python :: 2
Classifier: Programming Language :: Python :: 2.7
Classifier: Programming Language :: Python :: 3
Classifier: Programming Language :: Python :: 3.5
Classifier: Programming Language :: Python :: 3.6
Classifier: Programming Language :: Python :: 3.7
Classifier: Programming Language :: Python :: 3.8
Classifier: Programming Language :: Python :: 3.9
Classifier: Programming Language :: Python :: 3.10
Classifier: Programming Language :: Python :: 3.11
Classifier: Topic :: Software Development
Classifier: Topic :: Scientific/Engineering
License-File: LICENSE.txt
License-File: AUTHORS.rst
Requires-Dist: setuptools
Requires-Dist: colorama
Provides-Extra: dev
Requires-Dist: pytest (>=4.4) ; extra == 'dev'
Requires-Dist: pytest-cov ; extra == 'dev'
Requires-Dist: sphinx ; extra == 'dev'
Requires-Dist: sphinx-rtd-theme ; extra == 'dev'
Provides-Extra: docs
Requires-Dist: sphinx ; extra == 'docs'
Requires-Dist: sphinx-rtd-theme ; extra == 'docs'
Provides-Extra: tests
Requires-Dist: pytest (>=4.4) ; extra == 'tests'
Requires-Dist: pytest-cov ; extra == 'tests'
